docs/source/conf.py
examples/abl_states/run.py
examples/compare_rotors_pwakes/run.py
examples/compare_wakes/run.py
examples/dyn_wakes/run.py
examples/field_data_nc/run.py
examples/induction/run.py
examples/multi_height/run.py
examples/parameter_study/run.py
examples/power_mask/run.py
examples/quickstart/run.py
examples/random_timeseries/run.py
examples/scan_row/run.py
examples/sector_management/run.py
examples/sequential/run.py
examples/single_state/run.py
examples/states_lookup_table/run.py
examples/streamline_wakes/run.py
examples/tab_file/run.py
examples/timelines/run.py
examples/timeseries/run.py
examples/timeseries_slurm/run.py
examples/wind_rose/run.py
examples/yawed_wake/run.py
foxes/__init__.py
foxes/constants.py
foxes/variables.py
foxes/algorithms/__init__.py
foxes/algorithms/downwind/__init__.py
foxes/algorithms/downwind/downwind.py
foxes/algorithms/downwind/models/__init__.py
foxes/algorithms/downwind/models/farm_wakes_calc.py
foxes/algorithms/downwind/models/init_farm_data.py
foxes/algorithms/downwind/models/point_wakes_calc.py
foxes/algorithms/downwind/models/population.py
foxes/algorithms/downwind/models/reorder_farm_output.py
foxes/algorithms/downwind/models/set_amb_farm_results.py
foxes/algorithms/downwind/models/set_amb_point_results.py
foxes/algorithms/iterative/__init__.py
foxes/algorithms/iterative/iterative.py
foxes/algorithms/iterative/models/__init__.py
foxes/algorithms/iterative/models/convergence.py
foxes/algorithms/iterative/models/farm_wakes_calc.py
foxes/algorithms/iterative/models/urelax.py
foxes/algorithms/sequential/__init__.py
foxes/algorithms/sequential/sequential.py
foxes/algorithms/sequential/models/__init__.py
foxes/algorithms/sequential/models/plugin.py
foxes/algorithms/sequential/models/seq_state.py
foxes/config/__init__.py
foxes/config/conf.py
foxes/core/__init__.py
foxes/core/algorithm.py
foxes/core/axial_induction_model.py
foxes/core/data.py
foxes/core/data_calc_model.py
foxes/core/engine.py
foxes/core/farm_controller.py
foxes-1.7.1.dist-info/licenses/LICENSE
foxes-1.7.1.dist-info/METADATA
foxes-1.7.1.dist-info/WHEEL
foxes-1.7.1.dist-info/entry_points.txt
foxes-1.7.1.dist-info/top_level.txt
foxes-1.7.1.dist-info/RECORD
