Metadata-Version: 2.4
Name: foxes
Version: 1.7.1
Summary: Farm Optimization and eXtended yield Evaluation Software
Author: Jonas Schulte
Maintainer: Jonas Schulte
License: MIT License
Project-URL: Homepage, https://github.com/FraunhoferIWES/foxes
Project-URL: Documentation, https://fraunhoferiwes.github.io/foxes/index.html
Project-URL: Repository, https://github.com/FraunhoferIWES/foxes.git
Project-URL: Bug Tracker, https://github.com/FraunhoferIWES/foxes/issues
Project-URL: Changelog, https://github.com/FraunhoferIWES/foxes/blob/main/CHANGELOG.md
Keywords: Wind farm,Wake modelling,Wind farm optimization
Classifier: Topic :: Scientific/Engineering
Classifier: Intended Audience :: Developers
Classifier: Intended Audience :: Science/Research
Classifier: Programming Language :: Python :: 3
Classifier: Programming Language :: Python :: 3.9
Classifier: Programming Language :: Python :: 3.10
Classifier: Programming Language :: Python :: 3.11
Classifier: Programming Language :: Python :: 3.12
Classifier: Programming Language :: Python :: 3.13
Classifier: License :: OSI Approved :: MIT License
Classifier: Operating System :: OS Independent
Classifier: Development Status :: 4 - Beta
Requires-Python: <3.14,>=3.9
License-File: LICENSE
Requires-Dist: matplotlib>=3.8
Requires-Dist: numpy>=1.26
Requires-Dist: pandas>=2.0
Requires-Dist: scipy>=1.12
Requires-Dist: xarray>=2023
Requires-Dist: netcdf4>=1.5
Requires-Dist: pyyaml>=4.0
Requires-Dist: tqdm>=4.31.1
Requires-Dist: utm>=0.5
Provides-Extra: opt
Requires-Dist: foxes-opt>=0.6; extra == "opt"
Provides-Extra: dask
Requires-Dist: dask>=2022.0; extra == "dask"
Requires-Dist: distributed>=2022.0; extra == "dask"
Requires-Dist: dask-jobqueue>=0.8; extra == "dask"
Requires-Dist: setuptools>=61.0; extra == "dask"
Provides-Extra: doc
Requires-Dist: setuptools>=61.0; extra == "doc"
Requires-Dist: sphinx>=5.0; extra == "doc"
Requires-Dist: sphinx-immaterial>=0.10; extra == "doc"
Requires-Dist: myst-nb>=0.1; extra == "doc"
Requires-Dist: ipykernel>=5.0; extra == "doc"
Requires-Dist: ipywidgets>=5.0; extra == "doc"
Requires-Dist: m2r2>=0.2; extra == "doc"
Requires-Dist: lxml_html_clean>=0.4; extra == "doc"
Requires-Dist: dask>=2022.0; extra == "doc"
Requires-Dist: distributed>=2022.0; extra == "doc"
Provides-Extra: test
Requires-Dist: pytest>=7.0; extra == "test"
Requires-Dist: nbmake>1.0; extra == "test"
Requires-Dist: dask>=2022.0; extra == "test"
Requires-Dist: distributed>=2022.0; extra == "test"
Provides-Extra: dev
Requires-Dist: pre-commit>=0.1; extra == "dev"
Requires-Dist: objsize>=0.5; extra == "dev"
Requires-Dist: jupyter>=1.0; extra == "dev"
Dynamic: license-file
